dachs/__init__.py
dachs/__main__.py
dachs/additemstoattrs.py
dachs/dachsvalidators.py
dachs/equipment.py
dachs/helpers.py
dachs/main.py
dachs/metaclasses.py
dachs/readers.py
dachs/reagent.py
dachs/serialization.py
dachs/structure.py
dachs/synthesis.py
dachs-0.5.5.dist-info/licenses/AUTHORS.rst
dachs-0.5.5.dist-info/licenses/LICENSE
dachs-0.5.5.dist-info/METADATA
dachs-0.5.5.dist-info/WHEEL
dachs-0.5.5.dist-info/top_level.txt
dachs-0.5.5.dist-info/RECORD
