Metadata-Version: 2.4
Name: dachs
Version: 0.5.5
Summary: Database for Automation and Consistent Holistic Synthesis
Author-email: "Brian R. Pauw" <brian.pauw@bam.de>, "Glen J. Smales" <glen.smales@tugraz.at>, Ingo Breßler <ingo.bressler@bam.de>
License-Expression: GPL-3.0-or-later
Project-URL: homepage, https://BAMresearch.github.io/DACHS
Project-URL: documentation, https://BAMresearch.github.io/DACHS
Project-URL: repository, https://github.com/BAMresearch/DACHS
Project-URL: changelog, https://BAMresearch.github.io/DACHS/changelog.html
Classifier: Development Status :: 4 - Beta
Classifier: Operating System :: Unix
Classifier: Operating System :: POSIX
Classifier: Operating System :: MacOS
Classifier: Operating System :: Microsoft :: Windows
Classifier: Programming Language :: Python
Classifier: Programming Language :: Python :: 3
Classifier: Programming Language :: Python :: 3 :: Only
Classifier: Programming Language :: Python :: 3.11
Classifier: Programming Language :: Python :: 3.12
Classifier: Programming Language :: Python :: 3.13
Classifier: Programming Language :: Python :: Implementation :: CPython
Classifier: Framework :: Jupyter :: JupyterLab
Classifier: Topic :: Utilities
Classifier: Topic :: Scientific/Engineering
Classifier: Intended Audience :: Developers
Classifier: Intended Audience :: Science/Research
License-File: LICENSE
License-File: AUTHORS.rst
Requires-Dist: pint
Requires-Dist: mcsas3
Requires-Dist: graphviz
Requires-Dist: chempy
Requires-Dist: nexusformat
Requires-Dist: dash
Requires-Dist: openpyxl
Dynamic: license-file
